light_dataloader.py
light_dataloader-1.0.9.dist-info/licenses/LICENSE
light_dataloader-1.0.9.dist-info/METADATA
light_dataloader-1.0.9.dist-info/WHEEL
light_dataloader-1.0.9.dist-info/top_level.txt
light_dataloader-1.0.9.dist-info/RECORD
