Metadata-Version: 2.4
Name: light_dataloader
Version: 1.0.9
Summary: Faster DataLoader for datasets that are fully loaded into memory as tensors.
Author-email: Ivan Nikishev <nkshv2@gmail.com>
License: MIT License
Project-URL: Homepage, https://github.com/inikishev/light-dataloader
Project-URL: Repository, https://github.com/inikishev/light-dataloader
Project-URL: Issues, https://github.com/inikishev/light-dataloader/isses
Keywords: dataloader
Requires-Python: >=3.10
License-File: LICENSE
Requires-Dist: torch
Requires-Dist: numpy
Requires-Dist: more_itertools
Dynamic: license-file
